{
  "network": "arbitrumSepolia",
  "chainId": 421614,
  "isTestnet": true,
  "deployer": "0x3dbEf3f83bA2248fB500dd537436FC65E6F96BF1",
  "contracts": {
    "roseToken": "0xFD48CD135D4AB679610bf243b2269B4AFc0bc520",
    "vRose": "0x386845624885029Eff00e9bA3a44340E1aA01f9E",
    "roseTreasury": "0xdDdF1C8F065038aa9cCd9eDde128BBC2C9ea76BB",
    "roseMarketplace": "0x4522e2d2c86e7f3EF83a56b2F35A11ECFa8227aE",
    "roseReputation": "0x1031494c858e73A26244aAEF78ee8F8A671713FC",
    "roseGovernance": "0x43Dfb110683532d56d23f6A49E8Cd39a9dE1BB3A"
  },
  "tokenAddress": "0xFD48CD135D4AB679610bf243b2269B4AFc0bc520",
  "vRoseAddress": "0x386845624885029Eff00e9bA3a44340E1aA01f9E",
  "treasuryAddress": "0xdDdF1C8F065038aa9cCd9eDde128BBC2C9ea76BB",
  "marketplaceAddress": "0x4522e2d2c86e7f3EF83a56b2F35A11ECFa8227aE",
  "reputationAddress": "0x1031494c858e73A26244aAEF78ee8F8A671713FC",
  "governanceAddress": "0x43Dfb110683532d56d23f6A49E8Cd39a9dE1BB3A",
  "passportSignerAddress": "0x3dbef3f83ba2248fb500dd537436fc65e6f96bf1",
  "externalAddresses": {
    "usdc": "0xffbE12C95333816dA58C21FA2Eb3575342c811Fb",
    "tbtc": "0x4266041555835839040c7898665444312C7e476B",
    "xaut": "0x4Be3158F32385e0974a366e69d7853e94C7f85d3",
    "btcUsdFeed": "0x2F06144CBFF96Df8A0600186438bcb3812189C83",
    "xauUsdFeed": "0x7D9972E79fc32d2B6B6faE6b78E3f758C4d37260",
    "lifiDiamond": "0xC2e75BB2F65b1fFfEAf7A885B973a75723ef9680",
    "roseUsdFeed": "0x037D8201a19d0321d079237286085A89f9C0899a",
    "mockLiFi": {
      "target": "0xC2e75BB2F65b1fFfEAf7A885B973a75723ef9680",
      "interface": {
        "fragments": [
          {
            "type": "constructor",
            "inputs": [],
            "payable": false,
            "gas": null
          },
          {
            "type": "error",
            "inputs": [
              {
                "name": "token",
                "type": "address",
                "baseType": "address",
                "components": null,
                "arrayLength": null,
                "arrayChildren": null
              }
            ],
            "name": "SafeERC20FailedOperation"
          },
          {
            "type": "event",
            "inputs": [
              {
                "name": "fromToken",
                "type": "address",
                "baseType": "address",
                "indexed": true,
                "components": null,
                "arrayLength": null,
                "arrayChildren": null
              },
              {
                "name": "toToken",
                "type": "address",
                "baseType": "address",
                "indexed": true,
                "components": null,
                "arrayLength": null,
                "arrayChildren": null
              },
              {
                "name": "rate",
                "type": "uint256",
                "baseType": "uint256",
                "indexed": false,
                "components": null,
                "arrayLength": null,
                "arrayChildren": null
              }
            ],
            "name": "ExchangeRateSet",
            "anonymous": false
          },
          {
            "type": "event",
            "inputs": [
              {
                "name": "fromToken",
                "type": "address",
                "baseType": "address",
                "indexed": true,
                "components": null,
                "arrayLength": null,
                "arrayChildren": null
              },
              {
                "name": "toToken",
                "type": "address",
                "baseType": "address",
                "indexed": true,
                "components": null,
                "arrayLength": null,
                "arrayChildren": null
              },
              {
                "name": "amountIn",
                "type": "uint256",
                "baseType": "uint256",
                "indexed": false,
                "components": null,
                "arrayLength": null,
                "arrayChildren": null
              },
              {
                "name": "amountOut",
                "type": "uint256",
                "baseType": "uint256",
                "indexed": false,
                "components": null,
                "arrayLength": null,
                "arrayChildren": null
              },
              {
                "name": "recipient",
                "type": "address",
                "baseType": "address",
                "indexed": true,
                "components": null,
                "arrayLength": null,
                "arrayChildren": null
              }
            ],
            "name": "SwapExecuted",
            "anonymous": false
          },
          {
            "type": "fallback",
            "inputs": [
              {
                "name": "",
                "type": "bytes",
                "baseType": "bytes",
                "indexed": null,
                "components": null,
                "arrayLength": null,
                "arrayChildren": null
              }
            ],
            "payable": true
          },
          {
            "type": "function",
            "inputs": [],
            "name": "clearSwapHistory",
            "constant": false,
            "outputs": [],
            "stateMutability": "nonpayable",
            "payable": false,
            "gas": null
          },
          {
            "type": "function",
            "inputs": [
              {
                "name": "fromToken",
                "type": "address",
                "baseType": "address",
                "components": null,
                "arrayLength": null,
                "arrayChildren": null
              },
              {
                "name": "toToken",
                "type": "address",
                "baseType": "address",
                "components": null,
                "arrayLength": null,
                "arrayChildren": null
              },
              {
                "name": "amountIn",
                "type": "uint256",
                "baseType": "uint256",
                "components": null,
                "arrayLength": null,
                "arrayChildren": null
              },
              {
                "name": "minAmountOut",
                "type": "uint256",
                "baseType": "uint256",
                "components": null,
                "arrayLength": null,
                "arrayChildren": null
              },
              {
                "name": "recipient",
                "type": "address",
                "baseType": "address",
                "components": null,
                "arrayLength": null,
                "arrayChildren": null
              }
            ],
            "name": "encodeSwapCalldata",
            "constant": true,
            "outputs": [
              {
                "name": "",
                "type": "bytes",
                "baseType": "bytes",
                "components": null,
                "arrayLength": null,
                "arrayChildren": null
              }
            ],
            "stateMutability": "pure",
            "payable": false,
            "gas": null
          },
          {
            "type": "function",
            "inputs": [
              {
                "name": "",
                "type": "address",
                "baseType": "address",
                "components": null,
                "arrayLength": null,
                "arrayChildren": null
              },
              {
                "name": "",
                "type": "address",
                "baseType": "address",
                "components": null,
                "arrayLength": null,
                "arrayChildren": null
              }
            ],
            "name": "exchangeRates",
            "constant": true,
            "outputs": [
              {
                "name": "",
                "type": "uint256",
                "baseType": "uint256",
                "components": null,
                "arrayLength": null,
                "arrayChildren": null
              }
            ],
            "stateMutability": "view",
            "payable": false,
            "gas": null
          },
          {
            "type": "function",
            "inputs": [],
            "name": "getLastSwap",
            "constant": true,
            "outputs": [
              {
                "name": "fromToken",
                "type": "address",
                "baseType": "address",
                "components": null,
                "arrayLength": null,
                "arrayChildren": null
              },
              {
                "name": "toToken",
                "type": "address",
                "baseType": "address",
                "components": null,
                "arrayLength": null,
                "arrayChildren": null
              },
              {
                "name": "amountIn",
                "type": "uint256",
                "baseType": "uint256",
                "components": null,
                "arrayLength": null,
                "arrayChildren": null
              },
              {
                "name": "amountOut",
                "type": "uint256",
                "baseType": "uint256",
                "components": null,
                "arrayLength": null,
                "arrayChildren": null
              },
              {
                "name": "recipient",
                "type": "address",
                "baseType": "address",
                "components": null,
                "arrayLength": null,
                "arrayChildren": null
              },
              {
                "name": "timestamp",
                "type": "uint256",
                "baseType": "uint256",
                "components": null,
                "arrayLength": null,
                "arrayChildren": null
              }
            ],
            "stateMutability": "view",
            "payable": false,
            "gas": null
          },
          {
            "type": "function",
            "inputs": [
              {
                "name": "fromToken",
                "type": "address",
                "baseType": "address",
                "components": null,
                "arrayLength": null,
                "arrayChildren": null
              },
              {
                "name": "toToken",
                "type": "address",
                "baseType": "address",
                "components": null,
                "arrayLength": null,
                "arrayChildren": null
              },
              {
                "name": "amountIn",
                "type": "uint256",
                "baseType": "uint256",
                "components": null,
                "arrayLength": null,
                "arrayChildren": null
              }
            ],
            "name": "getQuote",
            "constant": true,
            "outputs": [
              {
                "name": "amountOut",
                "type": "uint256",
                "baseType": "uint256",
                "components": null,
                "arrayLength": null,
                "arrayChildren": null
              }
            ],
            "stateMutability": "view",
            "payable": false,
            "gas": null
          },
          {
            "type": "function",
            "inputs": [
              {
                "name": "index",
                "type": "uint256",
                "baseType": "uint256",
                "components": null,
                "arrayLength": null,
                "arrayChildren": null
              }
            ],
            "name": "getSwap",
            "constant": true,
            "outputs": [
              {
                "name": "fromToken",
                "type": "address",
                "baseType": "address",
                "components": null,
                "arrayLength": null,
                "arrayChildren": null
              },
              {
                "name": "toToken",
                "type": "address",
                "baseType": "address",
                "components": null,
                "arrayLength": null,
                "arrayChildren": null
              },
              {
                "name": "amountIn",
                "type": "uint256",
                "baseType": "uint256",
                "components": null,
                "arrayLength": null,
                "arrayChildren": null
              },
              {
                "name": "amountOut",
                "type": "uint256",
                "baseType": "uint256",
                "components": null,
                "arrayLength": null,
                "arrayChildren": null
              },
              {
                "name": "recipient",
                "type": "address",
                "baseType": "address",
                "components": null,
                "arrayLength": null,
                "arrayChildren": null
              },
              {
                "name": "timestamp",
                "type": "uint256",
                "baseType": "uint256",
                "components": null,
                "arrayLength": null,
                "arrayChildren": null
              }
            ],
            "stateMutability": "view",
            "payable": false,
            "gas": null
          },
          {
            "type": "function",
            "inputs": [],
            "name": "getSwapCount",
            "constant": true,
            "outputs": [
              {
                "name": "",
                "type": "uint256",
                "baseType": "uint256",
                "components": null,
                "arrayLength": null,
                "arrayChildren": null
              }
            ],
            "stateMutability": "view",
            "payable": false,
            "gas": null
          },
          {
            "type": "function",
            "inputs": [
              {
                "name": "fromToken",
                "type": "address",
                "baseType": "address",
                "components": null,
                "arrayLength": null,
                "arrayChildren": null
              },
              {
                "name": "toToken",
                "type": "address",
                "baseType": "address",
                "components": null,
                "arrayLength": null,
                "arrayChildren": null
              },
              {
                "name": "rate",
                "type": "uint256",
                "baseType": "uint256",
                "components": null,
                "arrayLength": null,
                "arrayChildren": null
              }
            ],
            "name": "setExchangeRate",
            "constant": false,
            "outputs": [],
            "stateMutability": "nonpayable",
            "payable": false,
            "gas": null
          },
          {
            "type": "function",
            "inputs": [
              {
                "name": "token",
                "type": "address",
                "baseType": "address",
                "components": null,
                "arrayLength": null,
                "arrayChildren": null
              },
              {
                "name": "key",
                "type": "bytes32",
                "baseType": "bytes32",
                "components": null,
                "arrayLength": null,
                "arrayChildren": null
              }
            ],
            "name": "setTokenAssetKey",
            "constant": false,
            "outputs": [],
            "stateMutability": "nonpayable",
            "payable": false,
            "gas": null
          },
          {
            "type": "function",
            "inputs": [
              {
                "name": "token",
                "type": "address",
                "baseType": "address",
                "components": null,
                "arrayLength": null,
                "arrayChildren": null
              },
              {
                "name": "decimals",
                "type": "uint8",
                "baseType": "uint8",
                "components": null,
                "arrayLength": null,
                "arrayChildren": null
              }
            ],
            "name": "setTokenDecimals",
            "constant": false,
            "outputs": [],
            "stateMutability": "nonpayable",
            "payable": false,
            "gas": null
          },
          {
            "type": "function",
            "inputs": [
              {
                "name": "_treasury",
                "type": "address",
                "baseType": "address",
                "components": null,
                "arrayLength": null,
                "arrayChildren": null
              }
            ],
            "name": "setTreasury",
            "constant": false,
            "outputs": [],
            "stateMutability": "nonpayable",
            "payable": false,
            "gas": null
          },
          {
            "type": "function",
            "inputs": [
              {
                "name": "",
                "type": "uint256",
                "baseType": "uint256",
                "components": null,
                "arrayLength": null,
                "arrayChildren": null
              }
            ],
            "name": "swapHistory",
            "constant": true,
            "outputs": [
              {
                "name": "fromToken",
                "type": "address",
                "baseType": "address",
                "components": null,
                "arrayLength": null,
                "arrayChildren": null
              },
              {
                "name": "toToken",
                "type": "address",
                "baseType": "address",
                "components": null,
                "arrayLength": null,
                "arrayChildren": null
              },
              {
                "name": "amountIn",
                "type": "uint256",
                "baseType": "uint256",
                "components": null,
                "arrayLength": null,
                "arrayChildren": null
              },
              {
                "name": "amountOut",
                "type": "uint256",
                "baseType": "uint256",
                "components": null,
                "arrayLength": null,
                "arrayChildren": null
              },
              {
                "name": "recipient",
                "type": "address",
                "baseType": "address",
                "components": null,
                "arrayLength": null,
                "arrayChildren": null
              },
              {
                "name": "timestamp",
                "type": "uint256",
                "baseType": "uint256",
                "components": null,
                "arrayLength": null,
                "arrayChildren": null
              }
            ],
            "stateMutability": "view",
            "payable": false,
            "gas": null
          },
          {
            "type": "function",
            "inputs": [
              {
                "name": "fromToken",
                "type": "address",
                "baseType": "address",
                "components": null,
                "arrayLength": null,
                "arrayChildren": null
              },
              {
                "name": "toToken",
                "type": "address",
                "baseType": "address",
                "components": null,
                "arrayLength": null,
                "arrayChildren": null
              },
              {
                "name": "amountIn",
                "type": "uint256",
                "baseType": "uint256",
                "components": null,
                "arrayLength": null,
                "arrayChildren": null
              },
              {
                "name": "minAmountOut",
                "type": "uint256",
                "baseType": "uint256",
                "components": null,
                "arrayLength": null,
                "arrayChildren": null
              },
              {
                "name": "recipient",
                "type": "address",
                "baseType": "address",
                "components": null,
                "arrayLength": null,
                "arrayChildren": null
              }
            ],
            "name": "swapSimple",
            "constant": false,
            "outputs": [
              {
                "name": "amountOut",
                "type": "uint256",
                "baseType": "uint256",
                "components": null,
                "arrayLength": null,
                "arrayChildren": null
              }
            ],
            "stateMutability": "nonpayable",
            "payable": false,
            "gas": null
          },
          {
            "type": "function",
            "inputs": [
              {
                "name": "",
                "type": "address",
                "baseType": "address",
                "components": null,
                "arrayLength": null,
                "arrayChildren": null
              }
            ],
            "name": "tokenAssetKeys",
            "constant": true,
            "outputs": [
              {
                "name": "",
                "type": "bytes32",
                "baseType": "bytes32",
                "components": null,
                "arrayLength": null,
                "arrayChildren": null
              }
            ],
            "stateMutability": "view",
            "payable": false,
            "gas": null
          },
          {
            "type": "function",
            "inputs": [
              {
                "name": "",
                "type": "address",
                "baseType": "address",
                "components": null,
                "arrayLength": null,
                "arrayChildren": null
              }
            ],
            "name": "tokenDecimals",
            "constant": true,
            "outputs": [
              {
                "name": "",
                "type": "uint8",
                "baseType": "uint8",
                "components": null,
                "arrayLength": null,
                "arrayChildren": null
              }
            ],
            "stateMutability": "view",
            "payable": false,
            "gas": null
          },
          {
            "type": "function",
            "inputs": [],
            "name": "treasury",
            "constant": true,
            "outputs": [
              {
                "name": "",
                "type": "address",
                "baseType": "address",
                "components": null,
                "arrayLength": null,
                "arrayChildren": null
              }
            ],
            "stateMutability": "view",
            "payable": false,
            "gas": null
          },
          {
            "type": "fallback",
            "inputs": [],
            "payable": true
          }
        ],
        "deploy": {
          "type": "constructor",
          "inputs": [],
          "payable": false,
          "gas": null
        },
        "fallback": {
          "type": "fallback",
          "inputs": [
            {
              "name": "",
              "type": "bytes",
              "baseType": "bytes",
              "indexed": null,
              "components": null,
              "arrayLength": null,
              "arrayChildren": null
            }
          ],
          "payable": true
        },
        "receive": true
      },
      "runner": "<SignerWithAddress 0x3dbEf3f83bA2248fB500dd537436FC65E6F96BF1>",
      "filters": {}
    }
  },
  "timestamp": "2025-12-11T16:05:39.593Z"
}